lib/__init__.py
lib/decoration.py
lib/descryptors.py
lib/errors.py
lib/metaclasses.py
lib/utils.py
lib/variables.py
logs/__init__.py
logs/config_server_log.py
server/__init__.py
server/core.py
server/server_db.py
server/server_gui.py
server/ui/__init__.py
tests/__init__.py
tests/test_client.py
tests/test_server.py
tests/test_utils.py
unit_tests/__init__.py
unit_tests/test_client.py
unit_tests/test_utils.py
mini_chat_server-0.0.2.dist-info/METADATA
mini_chat_server-0.0.2.dist-info/WHEEL
mini_chat_server-0.0.2.dist-info/top_level.txt
mini_chat_server-0.0.2.dist-info/RECORD
